yucebio_wdladaptor/__init__.py
yucebio_wdladaptor/version.py
yucebio_wdladaptor/backend/__init__.py
yucebio_wdladaptor/backend/aws.py
yucebio_wdladaptor/backend/base.py
yucebio_wdladaptor/backend/bcs.py
yucebio_wdladaptor/backend/sge.py
yucebio_wdladaptor/backend_v2/__init__.py
yucebio_wdladaptor/backend_v2/aws.py
yucebio_wdladaptor/backend_v2/base.py
yucebio_wdladaptor/backend_v2/bcs.py
yucebio_wdladaptor/backend_v2/sge.py
yucebio_wdladaptor/backend_v2/types.py
yucebio_wdladaptor/command/__init__.py
yucebio_wdladaptor/command/adaptor.py
yucebio_wdladaptor/command/adaptor_v2.py
yucebio_wdladaptor/command/api.py
yucebio_wdladaptor/command/base.py
yucebio_wdladaptor/command/config.py
yucebio_wdladaptor/command/login.py
yucebio_wdladaptor/command/monitor.py
yucebio_wdladaptor/util/__init__.py
yucebio_wdladaptor/util/api.py
yucebio_wdladaptor/util/cache.py
yucebio_wdladaptor/util/config.py
yucebio_wdladaptor/util/database.py
yucebio_wdladaptor/util/gist.py
yucebio_wdladaptor/util/input_processor.py
yucebio_wdladaptor/util/monitor.py
yucebio_wdladaptor/util/monitor_v2.py
yucebio_wdladaptor/util/types.py
yucebio_wdladaptor/util/wdl_processor.py
yucebio_wdladaptor/util/wdl_v1_parser.py
Yucebio_Wdladaptor-1.0.4.20211208.dist-info/METADATA
Yucebio_Wdladaptor-1.0.4.20211208.dist-info/WHEEL
Yucebio_Wdladaptor-1.0.4.20211208.dist-info/entry_points.txt
Yucebio_Wdladaptor-1.0.4.20211208.dist-info/top_level.txt
Yucebio_Wdladaptor-1.0.4.20211208.dist-info/RECORD
