Metadata-Version: 2.1
Name: Yucebio-Wdladaptor
Version: 1.0.4.20211208
Summary: Yucebio Wdl适配器
Home-page: UNKNOWN
Author: huangqingjun
Author-email: huangqingjun@yucebio.com
License: MIT
Platform: UNKNOWN
Classifier: License :: OSI Approved :: MIT License
Classifier: Programming Language :: Python
Classifier: Programming Language :: Python :: 3
Classifier: Programming Language :: Python :: 3.9
Classifier: Programming Language :: Python :: Implementation :: CPython
Classifier: Programming Language :: Python :: Implementation :: PyPy
Requires-Python: >=3.9
Requires-Dist: Yucebio-Config (>=0.1.0)
Requires-Dist: json5
Requires-Dist: click
Requires-Dist: requests
Requires-Dist: pymongo
Requires-Dist: batchcompute (>=2.1)
